LICENSE
MANIFEST.in
NOTICE
README.rst
VERSION
setup.py
src/sagemaker_tensorflow_container/__init__.py
src/sagemaker_tensorflow_container/deep_learning_container.py
src/sagemaker_tensorflow_container/s3_utils.py
src/sagemaker_tensorflow_container/training.py
src/sagemaker_tensorflow_training.egg-info/PKG-INFO
src/sagemaker_tensorflow_training.egg-info/SOURCES.txt
src/sagemaker_tensorflow_training.egg-info/dependency_links.txt
src/sagemaker_tensorflow_training.egg-info/requires.txt
src/sagemaker_tensorflow_training.egg-info/top_level.txt