Metadata-Version: 2.1
Name: sagemaker_tensorflow_training
Version: 20.5.0
Summary: Open source library for using TensorFlow to train models on on Amazon SageMaker.
Home-page: https://github.com/aws/sagemaker-tensorflow-training-toolkit
Author: Amazon Web Services
License: Apache License 2.0
Classifier: Development Status :: 5 - Production/Stable
Classifier: Intended Audience :: Developers
Classifier: Natural Language :: English
Classifier: License :: OSI Approved :: Apache Software License
Classifier: Programming Language :: Python
Classifier: Programming Language :: Python :: 3.7
Classifier: Programming Language :: Python :: 3.8
Classifier: Programming Language :: Python :: 3.9
License-File: LICENSE
License-File: NOTICE
Requires-Dist: sagemaker-training<=4.8.3,>=4.3.0
Requires-Dist: numpy<1.24
Requires-Dist: scipy
Requires-Dist: scikit-learn
Requires-Dist: pandas
Requires-Dist: Pillow
Requires-Dist: h5py
Provides-Extra: test
Requires-Dist: tox; extra == "test"
Requires-Dist: flake8; extra == "test"
Requires-Dist: pytest; extra == "test"
Requires-Dist: pytest-cov; extra == "test"
Requires-Dist: pytest-xdist; extra == "test"
Requires-Dist: pytest-rerunfailures; extra == "test"
Requires-Dist: mock; extra == "test"
Requires-Dist: sagemaker[local]>=2; extra == "test"
Requires-Dist: tensorflow<2.4; extra == "test"
Requires-Dist: docker-compose; extra == "test"
Requires-Dist: boto3==1.16.34; extra == "test"
Requires-Dist: python-dateutil<2.8.1,>=2.1; extra == "test"
Requires-Dist: botocore==1.19.34; extra == "test"
Requires-Dist: requests-mock; extra == "test"
Requires-Dist: awscli==1.18.194; extra == "test"
Requires-Dist: protobuf<3.20,>=3.9.2; extra == "test"
Requires-Dist: sagemaker-experiments==0.1.7; extra == "test"
Provides-Extra: benchmark
Requires-Dist: click; extra == "benchmark"
